LICENSE
MANIFEST.in
README.md
setup.py
NavierStokes/Advection.py
NavierStokes/Advection_Circular.py
NavierStokes/DiffusionFVM.py
NavierStokes/README.md
NavierStokes/SIMPLE.py
NavierStokes/TDMAsolver.py
NavierStokes/__init__.py
NavierStokes/__main__.py
NavierStokes/config.xml
NavierStokes.egg-info/PKG-INFO
NavierStokes.egg-info/SOURCES.txt
NavierStokes.egg-info/dependency_links.txt
NavierStokes.egg-info/entry_points.txt
NavierStokes.egg-info/requires.txt
NavierStokes.egg-info/top_level.txt
tests/__init__.py
tests/test_TDMAsolver.py