Metadata-Version: 2.1
Name: NavierStokes
Version: 0.3.0
Summary: Navier Stokes Calculator
Home-page: http://rickykim.net
Author: Kyu Mok (Ricky) Kim
Author-email: rickykim93@hotmail.com
License: UNKNOWN
Platform: UNKNOWN
